automatedcleaning/__init__.py
automatedcleaning/cleaning.py
automatedcleaning-1.1.dist-info/METADATA
automatedcleaning-1.1.dist-info/WHEEL
automatedcleaning-1.1.dist-info/top_level.txt
automatedcleaning-1.1.dist-info/RECORD
